bioformats_jar.py
bioformats_jar-2020.5.27.dist-info/LICENSE
bioformats_jar-2020.5.27.dist-info/METADATA
bioformats_jar-2020.5.27.dist-info/WHEEL
bioformats_jar-2020.5.27.dist-info/top_level.txt
bioformats_jar-2020.5.27.dist-info/RECORD
