Metadata-Version: 2.1
Name: bioformats-jar
Version: 2020.5.27
Summary: bioformats_package.jar installer for scyjava
Home-page: https://github.com/tlambert03/bioformats_jar
Author: Talley Lambert
Author-email: talley.lambert@gmail.com
License: GPL-2.0
Project-URL: Source Code, https://github.com/tlambert03/bioformats_jar
Classifier: Development Status :: 3 - Alpha
Classifier: License :: OSI Approved :: GNU General Public License v2 (GPLv2)
Classifier: Natural Language :: English
Classifier: Programming Language :: Python :: 3
Classifier: Programming Language :: Python :: 3 :: Only
Classifier: Programming Language :: Python :: 3.8
Classifier: Programming Language :: Python :: 3.9
Classifier: Programming Language :: Python :: 3.10
Requires-Python: >=3.8
License-File: LICENSE
Requires-Dist: scyjava
Provides-Extra: testing
Requires-Dist: pytest ; extra == 'testing'
Requires-Dist: pytest-cov ; extra == 'testing'
